{"name":"2023-07-17.json","content":{"lists":{"priorities":[{"content":"<input type=\"checkbox\"><span contenteditable=\"false\" style=\"\"> Душ</span>","checked":false},{"content":"<input type=\"checkbox\"><span contenteditable=\"false\" style=\"\"> Суп</span>","checked":false},{"content":"<input type=\"checkbox\"><span contenteditable=\"false\" style=\"\"> Куча мелких дел по дому</span>","checked":false}],"todo":[],"memento":[{"content":"<input type=\"checkbox\"><span contenteditable=\"false\">Обнять мужа</span>","checked":true},{"content":"<input type=\"checkbox\"><span contenteditable=\"false\">Физическая активность</span>","checked":false},{"content":"<input type=\"checkbox\"><span contenteditable=\"false\">Творчество</span>","checked":false},{"content":"<input type=\"checkbox\"><span contenteditable=\"false\">Английский</span>","checked":true},{"content":"<input type=\"checkbox\"><span contenteditable=\"false\">Чтение</span>","checked":false}]},"table":"<!--div id=\"time_overlay\">TEST</div--><div id=\"time_overlay\" start=\"00:00\" end=\"09:10\" style=\"top: 120px; height: 731.333px; background-color: rgba(0, 255, 255, 0.46);\">Сон<button id=\"time_delete_button\">X</button></div><div id=\"time_overlay\" start=\"09:10\" end=\"10:00\" style=\"top: 853.333px; height: 64.6667px; background-color: rgba(153, 102, 204, 0.46);\">Завтрак<button id=\"time_delete_button\">X</button></div><div id=\"time_overlay\" start=\"10:00\" end=\"11:00\" style=\"top: 920px; height: 78px; background-color: rgba(251, 96, 127, 0.46);\">Английский<button id=\"time_delete_button\">X</button></div><div id=\"time_overlay\" start=\"11:00\" end=\"13:25\" style=\"top: 1000px; height: 191.333px; background-color: rgba(153, 102, 204, 0.46);\">Готовка обеда, овощи, пластик, органика, крыльцо<button id=\"time_delete_button\">X</button></div><div id=\"time_overlay\" start=\"13:25\" end=\"14:10\" style=\"top: 1193.33px; height: 58px; background-color: rgba(255, 215, 0, 0.46);\">Обед, Ютуб, посуда<button id=\"time_delete_button\">X</button></div><div id=\"time_overlay\" start=\"14:10\" end=\"19:20\" style=\"top: 1253.33px; height: 411.333px; background-color: rgba(222, 49, 99, 0.46);\">Легенда, Телега<button id=\"time_delete_button\">X</button></div><div id=\"time_overlay\" start=\"19:20\" end=\"20:00\" style=\"top: 1666.67px; height: 51.3333px; background-color: rgba(255, 127, 80, 0.46);\">Ужин, Ютуб<button id=\"time_delete_button\">X</button></div><div id=\"time_overlay\" start=\"20:00\" end=\"20:50\" style=\"top: 1720px; height: 64.6667px; background-color: rgba(0, 72, 186, 0.46);\">Айзек<button id=\"time_delete_button\">X</button></div><div id=\"time_overlay\" start=\"20:50\" end=\"22:50\" style=\"top: 1786.67px; height: 158px; background-color: rgba(176, 191, 26, 0.46);\">Душ, Пикабу, Телега<button id=\"time_delete_button\">X</button></div><div id=\"time_overlay\" start=\"22:50\" end=\"23:59\" style=\"top: 1946.67px; height: 90px; background-color: rgba(251, 96, 127, 0.46);\">Айзек<button id=\"time_delete_button\">X</button></div>"}}