{"name":"2023-03-19.json","content":{"lists":{"priorities":[{"content":"<input type=\"checkbox\"><span contenteditable=\"false\" style=\"\">Душ</span>","checked":false},{"content":"<input type=\"checkbox\"><span contenteditable=\"false\" style=\"\"> Магазин</span>","checked":false},{"content":"<input type=\"checkbox\"><span contenteditable=\"false\" style=\"\"> Сериал</span>","checked":false}],"todo":[],"memento":[{"content":"<input type=\"checkbox\"><span contenteditable=\"false\">Обнять мужа</span>","checked":false},{"content":"<input type=\"checkbox\"><span contenteditable=\"false\">Физическая активность</span>","checked":false},{"content":"<input type=\"checkbox\"><span contenteditable=\"false\">Рисование</span>","checked":false},{"content":"<input type=\"checkbox\"><span contenteditable=\"false\">Английский</span>","checked":false},{"content":"<input type=\"checkbox\"><span contenteditable=\"false\">Чтение</span>","checked":false}]},"table":"<!--div id=\"time_overlay\">TEST</div--><div id=\"time_overlay\" start=\"00:00\" end=\"02:00\" style=\"top: 120px; height: 158px; background-color: rgba(124, 185, 232, 0.46);\">Пикабу, Легенда<button id=\"time_delete_button\">X</button></div><div id=\"time_overlay\" start=\"02:00\" end=\"09:40\" style=\"top: 280px; height: 611.333px; background-color: rgba(222, 49, 99, 0.46);\">Сон<button id=\"time_delete_button\">X</button></div><div id=\"time_overlay\" start=\"09:40\" end=\"12:00\" style=\"top: 893.333px; height: 184.667px; background-color: rgba(255, 127, 80, 0.46);\">Завтрак, телега, умывание<button id=\"time_delete_button\">X</button></div><div id=\"time_overlay\" start=\"12:00\" end=\"13:30\" style=\"top: 1080px; height: 118px; background-color: rgba(153, 102, 204, 0.46);\">Магазин, Пикабу, первый этаж<button id=\"time_delete_button\">X</button></div><div id=\"time_overlay\" start=\"13:30\" end=\"16:10\" style=\"top: 1200px; height: 211.333px; background-color: rgba(0, 255, 255, 0.46);\">Обед, сериал<button id=\"time_delete_button\">X</button></div><div id=\"time_overlay\" start=\"16:10\" end=\"18:10\" style=\"top: 1413.33px; height: 158px; background-color: rgba(141, 182, 0, 0.46);\">Сон<button id=\"time_delete_button\">X</button></div><div id=\"time_overlay\" start=\"18:10\" end=\"18:40\" style=\"top: 1573.33px; height: 38px; background-color: rgba(176, 191, 26, 0.46);\">Душ<button id=\"time_delete_button\">X</button></div><div id=\"time_overlay\" start=\"18:40\" end=\"22:00\" style=\"top: 1613.33px; height: 264.667px; background-color: rgba(124, 185, 232, 0.46);\">Ужин, разговоры с Катькой, сериал<button id=\"time_delete_button\">X</button></div>"}}